{"type":"FeatureCollection","features":[{"type":"Feature","properties":{"orginal:WS_OIDN":867811,"orginal:WS_UIDN":"867811_1","orginal:WS_GIDN":"867811_1","orginal:B_WK_OIDN":1735621,"orginal:E_WK_OIDN":1735622,"orginal:STATUS":4,"orginal:LBLSTATUS":"in gebruik","orginal:MORF":103,"orginal:LBLMORF":"weg bestaande uit één rijbaan","orginal:WEGCAT":"-8","orginal:LBLWEGCAT":"niet gekend","orginal:LSTRNMID":142355,"orginal:LSTRNM":"Poortershoekweg","orginal:RSTRNMID":142355,"orginal:RSTRNM":"Poortershoekweg","orginal:BEHEER":"32003","orginal:LBLBEHEER":"Stad Diksmuide","orginal:METHODE":2,"orginal:LBLMETHOD":"ingemeten","orginal:OPNDATUM":"20140220T143532","orginal:BEGINTIJD":"20140220T143532","orginal:BEGINORG":"AGIV","orginal:LBLBGNORG":"Agentschap voor Geografische Informatie Vlaanderen","orginal:TGBEP":1,"orginal:LBLTGBEP":"openbare weg","highway":"unclassified"},"geometry":{"type":"LineString","coordinates":[[2.775823473930359,51.047882951098615],[2.780367136001587,51.04524561821688],[2.780463695526123,51.04518153792796],[2.7805227041244507,51.04512083020404],[2.78053879737854,51.045066867715974],[2.780592441558838,51.044712737328155],[2.7806085348129272,51.044675637797525],[2.780667543411255,51.04461492941061],[2.7808231115341187,51.04451374858891],[2.782732063009484,51.043418480690505]]}}]}