{"type":"FeatureCollection","features":[{"type":"Feature","properties":{"orginal:WS_OIDN":950323,"orginal:WS_UIDN":"950323_1","orginal:WS_GIDN":"950323_1","orginal:B_WK_OIDN":1818560,"orginal:E_WK_OIDN":1900154,"orginal:STATUS":4,"orginal:LBLSTATUS":"in gebruik","orginal:MORF":103,"orginal:LBLMORF":"weg bestaande uit één rijbaan","orginal:WEGCAT":"-8","orginal:LBLWEGCAT":"niet gekend","orginal:LSTRNMID":61298,"orginal:LSTRNM":"Kasteeldreef","orginal:RSTRNMID":61298,"orginal:RSTRNM":"Kasteeldreef","orginal:BEHEER":"38025","orginal:LBLBEHEER":"Stad Veurne","orginal:METHODE":2,"orginal:LBLMETHOD":"ingemeten","orginal:OPNDATUM":"20140220T143532","orginal:BEGINTIJD":"20140220T143532","orginal:BEGINORG":"AGIV","orginal:LBLBGNORG":"Agentschap voor Geografische Informatie Vlaanderen","orginal:TGBEP":1,"orginal:LBLTGBEP":"openbare weg","highway":"unclassified"},"geometry":{"type":"LineString","coordinates":[[2.658262252807617,51.027421136727554],[2.6589971780776978,51.02784625147743]]}},{"type":"Feature","properties":{"orginal:WS_OIDN":833418,"orginal:WS_UIDN":"833418_1","orginal:WS_GIDN":"833418_1","orginal:B_WK_OIDN":1666835,"orginal:E_WK_OIDN":1798904,"orginal:STATUS":4,"orginal:LBLSTATUS":"in gebruik","orginal:MORF":103,"orginal:LBLMORF":"weg bestaande uit één rijbaan","orginal:WEGCAT":"-8","orginal:LBLWEGCAT":"niet gekend","orginal:LSTRNMID":61260,"orginal:LSTRNM":"Groeneplaats","orginal:RSTRNMID":61260,"orginal:RSTRNM":"Groeneplaats","orginal:BEHEER":"38025","orginal:LBLBEHEER":"Stad Veurne","orginal:METHODE":2,"orginal:LBLMETHOD":"ingemeten","orginal:OPNDATUM":"20140220T143532","orginal:BEGINTIJD":"20140220T143532","orginal:BEGINORG":"AGIV","orginal:LBLBGNORG":"Agentschap voor Geografische Informatie Vlaanderen","orginal:TGBEP":1,"orginal:LBLTGBEP":"openbare weg","highway":"unclassified"},"geometry":{"type":"LineString","coordinates":[[2.658970355987549,51.01683924678005],[2.65869140625,51.0170518531647],[2.658262252807617,51.01739944563039]]}},{"type":"Feature","properties":{"orginal:WS_OIDN":890720,"orginal:WS_UIDN":"890720_1","orginal:WS_GIDN":"890720_1","orginal:B_WK_OIDN":1781439,"orginal:E_WK_OIDN":1666833,"orginal:STATUS":4,"orginal:LBLSTATUS":"in gebruik","orginal:MORF":103,"orginal:LBLMORF":"weg bestaande uit één rijbaan","orginal:WEGCAT":"L1","orginal:LBLWEGCAT":"lokale weg type 1","orginal:LSTRNMID":61257,"orginal:LSTRNM":"Gouden-Hoofdstraat","orginal:RSTRNMID":61257,"orginal:RSTRNM":"Gouden-Hoofdstraat","orginal:BEHEER":"38025","orginal:LBLBEHEER":"Stad Veurne","orginal:METHODE":2,"orginal:LBLMETHOD":"ingemeten","orginal:OPNDATUM":"20140220T143532","orginal:BEGINTIJD":"20140220T143532","orginal:BEGINORG":"ABMV","orginal:LBLBGNORG":"MOW - Afdeling Beleid Mobiliteit en Verkeersveiligheid","orginal:TGBEP":1,"orginal:LBLTGBEP":"openbare weg","highway":"unclassified"},"geometry":{"type":"LineString","coordinates":[[2.658262252807617,51.01605968169619],[2.65869140625,51.016272291655184],[2.659313678741455,51.01658614267015]]}},{"type":"Feature","properties":{"orginal:WS_OIDN":897659,"orginal:WS_UIDN":"897659_1","orginal:WS_GIDN":"897659_1","orginal:B_WK_OIDN":1795317,"orginal:E_WK_OIDN":1955113,"orginal:STATUS":4,"orginal:LBLSTATUS":"in gebruik","orginal:MORF":103,"orginal:LBLMORF":"weg bestaande uit één rijbaan","orginal:WEGCAT":"-8","orginal:LBLWEGCAT":"niet gekend","orginal:LSTRNMID":61300,"orginal:LSTRNM":"Katjeshillestraat","orginal:RSTRNMID":61300,"orginal:RSTRNM":"Katjeshillestraat","orginal:BEHEER":"38025","orginal:LBLBEHEER":"Stad Veurne","orginal:METHODE":2,"orginal:LBLMETHOD":"ingemeten","orginal:OPNDATUM":"20140220T143532","orginal:BEGINTIJD":"20140220T143532","orginal:BEGINORG":"AGIV","orginal:LBLBGNORG":"Agentschap voor Geografische Informatie Vlaanderen","orginal:TGBEP":1,"orginal:LBLTGBEP":"openbare weg","highway":"unclassified"},"geometry":{"type":"LineString","coordinates":[[2.6680952310562134,51.02784625147743],[2.668406367301941,51.02763032066318],[2.6684921979904175,51.02757633780243],[2.6687121391296387,51.02745150219613],[2.6687657833099365,51.02740426701419],[2.6693451404571533,51.02638195092479],[2.6693934202194214,51.026267234181034]]}},{"type":"Feature","properties":{"orginal:WS_OIDN":878882,"orginal:WS_UIDN":"878882_1","orginal:WS_GIDN":"878882_1","orginal:B_WK_OIDN":1818620,"orginal:E_WK_OIDN":1905559,"orginal:STATUS":4,"orginal:LBLSTATUS":"in gebruik","orginal:MORF":103,"orginal:LBLMORF":"weg bestaande uit één rijbaan","orginal:WEGCAT":"-8","orginal:LBLWEGCAT":"niet gekend","orginal:LSTRNMID":61330,"orginal:LSTRNM":"Molendreef","orginal:RSTRNMID":61330,"orginal:RSTRNM":"Molendreef","orginal:BEHEER":"38025","orginal:LBLBEHEER":"Stad Veurne","orginal:METHODE":2,"orginal:LBLMETHOD":"ingemeten","orginal:OPNDATUM":"20140220T143532","orginal:BEGINTIJD":"20140220T143532","orginal:BEGINORG":"AGIV","orginal:LBLBGNORG":"Agentschap voor Geografische Informatie Vlaanderen","orginal:TGBEP":1,"orginal:LBLTGBEP":"openbare weg","highway":"unclassified"},"geometry":{"type":"LineString","coordinates":[[2.673652768135071,51.02784625147743],[2.6736098527908325,51.02762019888155],[2.673593759536743,51.02757633780243],[2.673545479774475,51.027488615519616]]}},{"type":"Feature","properties":{"orginal:WS_OIDN":970550,"orginal:WS_UIDN":"970550_2","orginal:WS_GIDN":"970550_2","orginal:B_WK_OIDN":1905570,"orginal:E_WK_OIDN":1759441,"orginal:STATUS":4,"orginal:LBLSTATUS":"in gebruik","orginal:MORF":103,"orginal:LBLMORF":"weg bestaande uit één rijbaan","orginal:WEGCAT":"S1","orginal:LBLWEGCAT":"secundaire weg type 1","orginal:LSTRNMID":61282,"orginal:LSTRNM":"Ieperse Steenweg","orginal:RSTRNMID":61282,"orginal:RSTRNM":"Ieperse Steenweg","orginal:BEHEER":"AWV315","orginal:LBLBEHEER":"Agentschap Wegen en Verkeer - District Oostende","orginal:METHODE":2,"orginal:LBLMETHOD":"ingemeten","orginal:OPNDATUM":"20161012T132044","orginal:BEGINTIJD":"20161012T134046","orginal:BEGINORG":"AWV","orginal:LBLBGNORG":"Agentschap Wegen en Verkeer","orginal:TGBEP":1,"orginal:LBLTGBEP":"openbare weg","highway":"unclassified"},"geometry":{"type":"LineString","coordinates":[[2.677568793296814,51.02784625147743],[2.6776546239852905,51.02757633780243],[2.678137421607971,51.026135646978304],[2.678362727165222,51.0254169718184]]}},{"type":"Feature","properties":{"orginal:WS_OIDN":855720,"orginal:WS_UIDN":"855720_1","orginal:WS_GIDN":"855720_1","orginal:B_WK_OIDN":1878279,"orginal:E_WK_OIDN":1880634,"orginal:STATUS":4,"orginal:LBLSTATUS":"in gebruik","orginal:MORF":103,"orginal:LBLMORF":"weg bestaande uit één rijbaan","orginal:WEGCAT":"-8","orginal:LBLWEGCAT":"niet gekend","orginal:LSTRNMID":61224,"orginal:LSTRNM":"Boonakkerstraat","orginal:RSTRNMID":61224,"orginal:RSTRNM":"Boonakkerstraat","orginal:BEHEER":"38025","orginal:LBLBEHEER":"Stad Veurne","orginal:METHODE":2,"orginal:LBLMETHOD":"ingemeten","orginal:OPNDATUM":"20140220T143532","orginal:BEGINTIJD":"20140220T143532","orginal:BEGINORG":"AGIV","orginal:LBLBGNORG":"Agentschap voor Geografische Informatie Vlaanderen","orginal:TGBEP":1,"orginal:LBLTGBEP":"openbare weg","highway":"unclassified"},"geometry":{"type":"LineString","coordinates":[[2.6614487171173096,51.02784625147743],[2.661792039871216,51.02757633780243],[2.6628005504608154,51.02678008330358],[2.662881016731262,51.02670248149806],[2.663106322288513,51.02642918714852],[2.6637446880340576,51.02554518698278],[2.663782238960266,51.025484453528065]]}},{"type":"Feature","properties":{"orginal:WS_OIDN":940317,"orginal:WS_UIDN":"940317_1","orginal:WS_GIDN":"940317_1","orginal:B_WK_OIDN":1880633,"orginal:E_WK_OIDN":1880634,"orginal:STATUS":4,"orginal:LBLSTATUS":"in gebruik","orginal:MORF":103,"orginal:LBLMORF":"weg bestaande uit één rijbaan","orginal:WEGCAT":"-8","orginal:LBLWEGCAT":"niet gekend","orginal:LSTRNMID":61298,"orginal:LSTRNM":"Kasteeldreef","orginal:RSTRNMID":61298,"orginal:RSTRNM":"Kasteeldreef","orginal:BEHEER":"38025","orginal:LBLBEHEER":"Stad Veurne","orginal:METHODE":2,"orginal:LBLMETHOD":"ingemeten","orginal:OPNDATUM":"20140220T143532","orginal:BEGINTIJD":"20140220T143532","orginal:BEGINORG":"AGIV","orginal:LBLBGNORG":"Agentschap voor Geografische Informatie Vlaanderen","orginal:TGBEP":1,"orginal:LBLTGBEP":"openbare weg","highway":"unclassified"},"geometry":{"type":"LineString","coordinates":[[2.661089301109314,51.02465779581553],[2.661368250846863,51.024759020000914],[2.663782238960266,51.025484453528065]]}},{"type":"Feature","properties":{"orginal:WS_OIDN":929325,"orginal:WS_UIDN":"929325_1","orginal:WS_GIDN":"929325_1","orginal:B_WK_OIDN":1880634,"orginal:E_WK_OIDN":1782245,"orginal:STATUS":4,"orginal:LBLSTATUS":"in gebruik","orginal:MORF":103,"orginal:LBLMORF":"weg bestaande uit één rijbaan","orginal:WEGCAT":"-8","orginal:LBLWEGCAT":"niet gekend","orginal:LSTRNMID":61224,"orginal:LSTRNM":"Boonakkerstraat","orginal:RSTRNMID":61224,"orginal:RSTRNM":"Boonakkerstraat","orginal:BEHEER":"38025","orginal:LBLBEHEER":"Stad Veurne","orginal:METHODE":2,"orginal:LBLMETHOD":"ingemeten","orginal:OPNDATUM":"20140220T143532","orginal:BEGINTIJD":"20140220T143532","orginal:BEGINORG":"AGIV","orginal:LBLBGNORG":"Agentschap voor Geografische Informatie Vlaanderen","orginal:TGBEP":1,"orginal:LBLTGBEP":"openbare weg","highway":"unclassified"},"geometry":{"type":"LineString","coordinates":[[2.663782238960266,51.025484453528065],[2.6641523838043213,51.02490748173972],[2.6641952991485596,51.02482312853735],[2.664211392402649,51.02476576827209]]}},{"type":"Feature","properties":{"orginal:WS_OIDN":977557,"orginal:WS_UIDN":"977557_1","orginal:WS_GIDN":"977557_1","orginal:B_WK_OIDN":1955113,"orginal:E_WK_OIDN":1782245,"orginal:STATUS":4,"orginal:LBLSTATUS":"in gebruik","orginal:MORF":103,"orginal:LBLMORF":"weg bestaande uit één rijbaan","orginal:WEGCAT":"-8","orginal:LBLWEGCAT":"niet gekend","orginal:LSTRNMID":61321,"orginal:LSTRNM":"Lobbestraat","orginal:RSTRNMID":61321,"orginal:RSTRNM":"Lobbestraat","orginal:BEHEER":"38025","orginal:LBLBEHEER":"Stad Veurne","orginal:METHODE":2,"orginal:LBLMETHOD":"ingemeten","orginal:OPNDATUM":"20140220T143532","orginal:BEGINTIJD":"20140220T143532","orginal:BEGINORG":"AGIV","orginal:LBLBGNORG":"Agentschap voor Geografische Informatie Vlaanderen","orginal:TGBEP":1,"orginal:LBLTGBEP":"openbare weg","highway":"unclassified"},"geometry":{"type":"LineString","coordinates":[[2.6693934202194214,51.026267234181034],[2.6686638593673706,51.026068166216646],[2.6684921979904175,51.0259939372653],[2.6679235696792603,51.02564640923046],[2.6674407720565796,51.02532924544897],[2.667279839515686,51.0252550153144],[2.667226195335388,51.025238144812676],[2.667135000228882,51.02522464840689],[2.6661747694015503,51.02526176351333],[2.666029930114746,51.02526176351333],[2.665885090827942,51.02525164121454],[2.6657509803771973,51.02523139661028],[2.665455937385559,51.02516391453224],[2.6652520895004272,51.02509643235592],[2.6649516820907593,51.024974964191074],[2.6647424697875977,51.02490073348915],[2.664479613304138,51.02482650266839],[2.664211392402649,51.02476576827209]]}},{"type":"Feature","properties":{"orginal:WS_OIDN":888956,"orginal:WS_UIDN":"888956_1","orginal:WS_GIDN":"888956_1","orginal:B_WK_OIDN":1858654,"orginal:E_WK_OIDN":1955113,"orginal:STATUS":4,"orginal:LBLSTATUS":"in gebruik","orginal:MORF":103,"orginal:LBLMORF":"weg bestaande uit één rijbaan","orginal:WEGCAT":"-8","orginal:LBLWEGCAT":"niet gekend","orginal:LSTRNMID":61321,"orginal:LSTRNM":"Lobbestraat","orginal:RSTRNMID":61321,"orginal:RSTRNM":"Lobbestraat","orginal:BEHEER":"38025","orginal:LBLBEHEER":"Stad Veurne","orginal:METHODE":2,"orginal:LBLMETHOD":"ingemeten","orginal:OPNDATUM":"20140220T143532","orginal:BEGINTIJD":"20140220T143532","orginal:BEGINORG":"AGIV","orginal:LBLBGNORG":"Agentschap voor Geografische Informatie Vlaanderen","orginal:TGBEP":1,"orginal:LBLTGBEP":"openbare weg","highway":"unclassified"},"geometry":{"type":"LineString","coordinates":[[2.669506072998047,51.02627398223265],[2.6693934202194214,51.026267234181034]]}},{"type":"Feature","properties":{"orginal:WS_OIDN":891123,"orginal:WS_UIDN":"891123_1","orginal:WS_GIDN":"891123_1","orginal:B_WK_OIDN":1782245,"orginal:E_WK_OIDN":1593713,"orginal:STATUS":4,"orginal:LBLSTATUS":"in gebruik","orginal:MORF":103,"orginal:LBLMORF":"weg bestaande uit één rijbaan","orginal:WEGCAT":"-8","orginal:LBLWEGCAT":"niet gekend","orginal:LSTRNMID":61224,"orginal:LSTRNM":"Boonakkerstraat","orginal:RSTRNMID":61224,"orginal:RSTRNM":"Boonakkerstraat","orginal:BEHEER":"38025","orginal:LBLBEHEER":"Stad Veurne","orginal:METHODE":2,"orginal:LBLMETHOD":"ingemeten","orginal:OPNDATUM":"20140220T143532","orginal:BEGINTIJD":"20140220T143532","orginal:BEGINORG":"AGIV","orginal:LBLBGNORG":"Agentschap voor Geografische Informatie Vlaanderen","orginal:TGBEP":1,"orginal:LBLTGBEP":"openbare weg","highway":"unclassified"},"geometry":{"type":"LineString","coordinates":[[2.664211392402649,51.02476576827209],[2.6642274856567383,51.02445534678159],[2.664254307746887,51.0243102577634],[2.664307951927185,51.024134800669685],[2.6643937826156616,51.023881736384084],[2.664458155632019,51.02372314872767],[2.6646244525909424,51.02340597178724],[2.664656639099121,51.02331824161212],[2.664656639099121,51.02325075674901],[2.664533257484436,51.02291333095994],[2.6644527912139893,51.022660260006404],[2.664361596107483,51.022305958350586],[2.6642489433288574,51.02150623894548],[2.664232850074768,51.021307150535506],[2.6642489433288574,51.02125316031086],[2.6642757654190063,51.0211755492528],[2.664307951927185,51.02111481007324],[2.6644957065582275,51.02087522697792],[2.6650911569595337,51.020217210698576],[2.6654988527297974,51.0196739184243],[2.6658207178115845,51.01919811064445],[2.6660406589508057,51.01888765187201]]}},{"type":"Feature","properties":{"orginal:WS_OIDN":929433,"orginal:WS_UIDN":"929433_1","orginal:WS_GIDN":"929433_1","orginal:B_WK_OIDN":1948158,"orginal:E_WK_OIDN":1914102,"orginal:STATUS":4,"orginal:LBLSTATUS":"in gebruik","orginal:MORF":103,"orginal:LBLMORF":"weg bestaande uit één rijbaan","orginal:WEGCAT":"L1","orginal:LBLWEGCAT":"lokale weg type 1","orginal:LSTRNMID":61257,"orginal:LSTRNM":"Gouden-Hoofdstraat","orginal:RSTRNMID":61257,"orginal:RSTRNM":"Gouden-Hoofdstraat","orginal:BEHEER":"38025","orginal:LBLBEHEER":"Stad Veurne","orginal:METHODE":2,"orginal:LBLMETHOD":"ingemeten","orginal:OPNDATUM":"20140220T143532","orginal:BEGINTIJD":"20140220T143532","orginal:BEGINORG":"ABMV","orginal:LBLBGNORG":"MOW - Afdeling Beleid Mobiliteit en Verkeersveiligheid","orginal:TGBEP":1,"orginal:LBLTGBEP":"openbare weg","highway":"unclassified"},"geometry":{"type":"LineString","coordinates":[[2.661861777305603,51.01766941856317],[2.6620012521743774,51.01771666366483],[2.662462592124939,51.0178212776471],[2.6625001430511475,51.01783815084798]]}},{"type":"Feature","properties":{"orginal:WS_OIDN":997202,"orginal:WS_UIDN":"997202_1","orginal:WS_GIDN":"997202_1","orginal:B_WK_OIDN":1973607,"orginal:E_WK_OIDN":1914102,"orginal:STATUS":4,"orginal:LBLSTATUS":"in gebruik","orginal:MORF":103,"orginal:LBLMORF":"weg bestaande uit één rijbaan","orginal:WEGCAT":"L1","orginal:LBLWEGCAT":"lokale weg type 1","orginal:LSTRNMID":61257,"orginal:LSTRNM":"Gouden-Hoofdstraat","orginal:RSTRNMID":61257,"orginal:RSTRNM":"Gouden-Hoofdstraat","orginal:BEHEER":"38025","orginal:LBLBEHEER":"Stad Veurne","orginal:METHODE":2,"orginal:LBLMETHOD":"ingemeten","orginal:OPNDATUM":"20150504T102053","orginal:BEGINTIJD":"20150504T103707","orginal:BEGINORG":"AGIV","orginal:LBLBGNORG":"Agentschap voor Geografische Informatie Vlaanderen","orginal:TGBEP":1,"orginal:LBLTGBEP":"openbare weg","highway":"unclassified"},"geometry":{"type":"LineString","coordinates":[[2.6633262634277344,51.018027130277915],[2.662757635116577,51.017892145049416],[2.6625001430511475,51.01783815084798]]}},{"type":"Feature","properties":{"orginal:WS_OIDN":997203,"orginal:WS_UIDN":"997203_1","orginal:WS_GIDN":"997203_1","orginal:B_WK_OIDN":1973607,"orginal:E_WK_OIDN":1914102,"orginal:STATUS":4,"orginal:LBLSTATUS":"in gebruik","orginal:MORF":103,"orginal:LBLMORF":"weg bestaande uit één rijbaan","orginal:WEGCAT":"L1","orginal:LBLWEGCAT":"lokale weg type 1","orginal:LSTRNMID":61257,"orginal:LSTRNM":"Gouden-Hoofdstraat","orginal:RSTRNMID":61257,"orginal:RSTRNM":"Gouden-Hoofdstraat","orginal:BEHEER":"38025","orginal:LBLBEHEER":"Stad Veurne","orginal:METHODE":1,"orginal:LBLMETHOD":"ingeschetst","orginal:OPNDATUM":"20150504T102053","orginal:BEGINTIJD":"20150504T103707","orginal:BEGINORG":"AGIV","orginal:LBLBGNORG":"Agentschap voor Geografische Informatie Vlaanderen","orginal:TGBEP":1,"orginal:LBLTGBEP":"openbare weg","highway":"unclassified"},"geometry":{"type":"LineString","coordinates":[[2.6633262634277344,51.018027130277915],[2.66294002532959,51.018003507891336],[2.6627683639526367,51.017959637712806],[2.6625001430511475,51.01783815084798]]}},{"type":"Feature","properties":{"orginal:WS_OIDN":833417,"orginal:WS_UIDN":"833417_1","orginal:WS_GIDN":"833417_1","orginal:B_WK_OIDN":1666833,"orginal:E_WK_OIDN":1666835,"orginal:STATUS":4,"orginal:LBLSTATUS":"in gebruik","orginal:MORF":103,"orginal:LBLMORF":"weg bestaande uit één rijbaan","orginal:WEGCAT":"-8","orginal:LBLWEGCAT":"niet gekend","orginal:LSTRNMID":61260,"orginal:LSTRNM":"Groeneplaats","orginal:RSTRNMID":61260,"orginal:RSTRNM":"Groeneplaats","orginal:BEHEER":"38025","orginal:LBLBEHEER":"Stad Veurne","orginal:METHODE":2,"orginal:LBLMETHOD":"ingemeten","orginal:OPNDATUM":"20140220T143532","orginal:BEGINTIJD":"20140220T143532","orginal:BEGINORG":"AGIV","orginal:LBLBGNORG":"Agentschap voor Geografische Informatie Vlaanderen","orginal:TGBEP":1,"orginal:LBLTGBEP":"openbare weg","highway":"unclassified"},"geometry":{"type":"LineString","coordinates":[[2.659313678741455,51.01658614267015],[2.659088373184204,51.016758253615194],[2.658970355987549,51.01683924678005]]}},{"type":"Feature","properties":{"orginal:WS_OIDN":893858,"orginal:WS_UIDN":"893858_1","orginal:WS_GIDN":"893858_1","orginal:B_WK_OIDN":1666833,"orginal:E_WK_OIDN":1787716,"orginal:STATUS":4,"orginal:LBLSTATUS":"in gebruik","orginal:MORF":103,"orginal:LBLMORF":"weg bestaande uit één rijbaan","orginal:WEGCAT":"L1","orginal:LBLWEGCAT":"lokale weg type 1","orginal:LSTRNMID":61257,"orginal:LSTRNM":"Gouden-Hoofdstraat","orginal:RSTRNMID":61257,"orginal:RSTRNM":"Gouden-Hoofdstraat","orginal:BEHEER":"38025","orginal:LBLBEHEER":"Stad Veurne","orginal:METHODE":2,"orginal:LBLMETHOD":"ingemeten","orginal:OPNDATUM":"20140220T143532","orginal:BEGINTIJD":"20140220T143532","orginal:BEGINORG":"ABMV","orginal:LBLBGNORG":"MOW - Afdeling Beleid Mobiliteit en Verkeersveiligheid","orginal:TGBEP":1,"orginal:LBLTGBEP":"openbare weg","highway":"unclassified"},"geometry":{"type":"LineString","coordinates":[[2.659313678741455,51.01658614267015],[2.659560441970825,51.01670425809337],[2.6596838235855103,51.01675487889693]]}},{"type":"Feature","properties":{"orginal:WS_OIDN":974079,"orginal:WS_UIDN":"974079_1","orginal:WS_GIDN":"974079_1","orginal:B_WK_OIDN":1787716,"orginal:E_WK_OIDN":1948158,"orginal:STATUS":4,"orginal:LBLSTATUS":"in gebruik","orginal:MORF":103,"orginal:LBLMORF":"weg bestaande uit één rijbaan","orginal:WEGCAT":"L1","orginal:LBLWEGCAT":"lokale weg type 1","orginal:LSTRNMID":61257,"orginal:LSTRNM":"Gouden-Hoofdstraat","orginal:RSTRNMID":61257,"orginal:RSTRNM":"Gouden-Hoofdstraat","orginal:BEHEER":"38025","orginal:LBLBEHEER":"Stad Veurne","orginal:METHODE":2,"orginal:LBLMETHOD":"ingemeten","orginal:OPNDATUM":"20140220T143532","orginal:BEGINTIJD":"20140220T143532","orginal:BEGINORG":"ABMV","orginal:LBLBGNORG":"MOW - Afdeling Beleid Mobiliteit en Verkeersveiligheid","orginal:TGBEP":1,"orginal:LBLTGBEP":"openbare weg","highway":"unclassified"},"geometry":{"type":"LineString","coordinates":[[2.6596838235855103,51.01675487889693],[2.6599842309951782,51.01686286975982],[2.6605796813964844,51.017038354375615],[2.6607567071914673,51.01709572420211],[2.6610249280929565,51.01721383832731],[2.661759853363037,51.01762217341343],[2.661861777305603,51.01766941856317]]}},{"type":"Feature","properties":{"orginal:WS_OIDN":826888,"orginal:WS_UIDN":"826888_1","orginal:WS_GIDN":"826888_1","orginal:B_WK_OIDN":461459,"orginal:E_WK_OIDN":1787716,"orginal:STATUS":4,"orginal:LBLSTATUS":"in gebruik","orginal:MORF":103,"orginal:LBLMORF":"weg bestaande uit één rijbaan","orginal:WEGCAT":"-8","orginal:LBLWEGCAT":"niet gekend","orginal:LSTRNMID":61417,"orginal:LSTRNM":"Vinkemstraat","orginal:RSTRNMID":61417,"orginal:RSTRNM":"Vinkemstraat","orginal:BEHEER":"38025","orginal:LBLBEHEER":"Stad Veurne","orginal:METHODE":2,"orginal:LBLMETHOD":"ingemeten","orginal:OPNDATUM":"20140220T143532","orginal:BEGINTIJD":"20140220T143532","orginal:BEGINORG":"AGIV","orginal:LBLBGNORG":"Agentschap voor Geografische Informatie Vlaanderen","orginal:TGBEP":1,"orginal:LBLTGBEP":"openbare weg","highway":"unclassified"},"geometry":{"type":"LineString","coordinates":[[2.660858631134033,51.015485967418726],[2.6608049869537354,51.015519715513875],[2.6596838235855103,51.01675487889693]]}},{"type":"Feature","properties":{"orginal:WS_OIDN":826887,"orginal:WS_UIDN":"826887_1","orginal:WS_GIDN":"826887_1","orginal:B_WK_OIDN":1799012,"orginal:E_WK_OIDN":461459,"orginal:STATUS":4,"orginal:LBLSTATUS":"in gebruik","orginal:MORF":103,"orginal:LBLMORF":"weg bestaande uit één rijbaan","orginal:WEGCAT":"-8","orginal:LBLWEGCAT":"niet gekend","orginal:LSTRNMID":61417,"orginal:LSTRNM":"Vinkemstraat","orginal:RSTRNMID":61417,"orginal:RSTRNM":"Vinkemstraat","orginal:BEHEER":"38025","orginal:LBLBEHEER":"Stad Veurne","orginal:METHODE":2,"orginal:LBLMETHOD":"ingemeten","orginal:OPNDATUM":"20140220T143532","orginal:BEGINTIJD":"20140220T143532","orginal:BEGINORG":"AGIV","orginal:LBLBGNORG":"Agentschap voor Geografische Informatie Vlaanderen","orginal:TGBEP":1,"orginal:LBLTGBEP":"openbare weg","highway":"unclassified"},"geometry":{"type":"LineString","coordinates":[[2.6619046926498413,51.01591456640253],[2.661867141723633,51.015850445546704],[2.661336064338684,51.015641208453104],[2.661110758781433,51.01556358800087],[2.660858631134033,51.015485967418726]]}},{"type":"Feature","properties":{"orginal:WS_OIDN":873242,"orginal:WS_UIDN":"873242_1","orginal:WS_GIDN":"873242_1","orginal:B_WK_OIDN":1948158,"orginal:E_WK_OIDN":1746484,"orginal:STATUS":4,"orginal:LBLSTATUS":"in gebruik","orginal:MORF":103,"orginal:LBLMORF":"weg bestaande uit één rijbaan","orginal:WEGCAT":"-8","orginal:LBLWEGCAT":"niet gekend","orginal:LSTRNMID":61438,"orginal:LSTRNM":"Zomerweg","orginal:RSTRNMID":61438,"orginal:RSTRNM":"Zomerweg","orginal:BEHEER":"38025","orginal:LBLBEHEER":"Stad Veurne","orginal:METHODE":2,"orginal:LBLMETHOD":"ingemeten","orginal:OPNDATUM":"20140220T143532","orginal:BEGINTIJD":"20140220T143532","orginal:BEGINORG":"AGIV","orginal:LBLBGNORG":"Agentschap voor Geografische Informatie Vlaanderen","orginal:TGBEP":1,"orginal:LBLTGBEP":"openbare weg","highway":"unclassified"},"geometry":{"type":"LineString","coordinates":[[2.661861777305603,51.01766941856317],[2.6620227098464966,51.01742981766381],[2.6623767614364624,51.016943862741954],[2.6625537872314453,51.01667051086028]]}},{"type":"Feature","properties":{"orginal:WS_OIDN":972735,"orginal:WS_UIDN":"972735_1","orginal:WS_GIDN":"972735_1","orginal:B_WK_OIDN":1746484,"orginal:E_WK_OIDN":1858646,"orginal:STATUS":4,"orginal:LBLSTATUS":"in gebruik","orginal:MORF":103,"orginal:LBLMORF":"weg bestaande uit één rijbaan","orginal:WEGCAT":"-8","orginal:LBLWEGCAT":"niet gekend","orginal:LSTRNMID":61438,"orginal:LSTRNM":"Zomerweg","orginal:RSTRNMID":61438,"orginal:RSTRNM":"Zomerweg","orginal:BEHEER":"38025","orginal:LBLBEHEER":"Stad Veurne","orginal:METHODE":2,"orginal:LBLMETHOD":"ingemeten","orginal:OPNDATUM":"20140220T143532","orginal:BEGINTIJD":"20140220T143532","orginal:BEGINORG":"AGIV","orginal:LBLBGNORG":"Agentschap voor Geografische Informatie Vlaanderen","orginal:TGBEP":1,"orginal:LBLTGBEP":"openbare weg","highway":"unclassified"},"geometry":{"type":"LineString","coordinates":[[2.6625537872314453,51.01667051086028],[2.6626557111740112,51.01650514906322],[2.662811279296875,51.01621492080989],[2.6628541946411133,51.016154175131675]]}},{"type":"Feature","properties":{"orginal:WS_OIDN":899506,"orginal:WS_UIDN":"899506_1","orginal:WS_GIDN":"899506_1","orginal:B_WK_OIDN":1799010,"orginal:E_WK_OIDN":1799012,"orginal:STATUS":4,"orginal:LBLSTATUS":"in gebruik","orginal:MORF":103,"orginal:LBLMORF":"weg bestaande uit één rijbaan","orginal:WEGCAT":"-8","orginal:LBLWEGCAT":"niet gekend","orginal:LSTRNMID":61417,"orginal:LSTRNM":"Vinkemstraat","orginal:RSTRNMID":61417,"orginal:RSTRNM":"Vinkemstraat","orginal:BEHEER":"38025","orginal:LBLBEHEER":"Stad Veurne","orginal:METHODE":2,"orginal:LBLMETHOD":"ingemeten","orginal:OPNDATUM":"20140220T143532","orginal:BEGINTIJD":"20140220T143532","orginal:BEGINORG":"AGIV","orginal:LBLBGNORG":"Agentschap voor Geografische Informatie Vlaanderen","orginal:TGBEP":1,"orginal:LBLTGBEP":"openbare weg","highway":"unclassified"},"geometry":{"type":"LineString","coordinates":[[2.661615014076233,51.01637015940392],[2.6616954803466797,51.016221670324796],[2.6619046926498413,51.01591456640253]]}},{"type":"Feature","properties":{"orginal:WS_OIDN":929323,"orginal:WS_UIDN":"929323_1","orginal:WS_GIDN":"929323_1","orginal:B_WK_OIDN":1799012,"orginal:E_WK_OIDN":1858646,"orginal:STATUS":4,"orginal:LBLSTATUS":"in gebruik","orginal:MORF":103,"orginal:LBLMORF":"weg bestaande uit één rijbaan","orginal:WEGCAT":"-8","orginal:LBLWEGCAT":"niet gekend","orginal:LSTRNMID":61417,"orginal:LSTRNM":"Vinkemstraat","orginal:RSTRNMID":61417,"orginal:RSTRNM":"Vinkemstraat","orginal:BEHEER":"38025","orginal:LBLBEHEER":"Stad Veurne","orginal:METHODE":2,"orginal:LBLMETHOD":"ingemeten","orginal:OPNDATUM":"20140220T143532","orginal:BEGINTIJD":"20140220T143532","orginal:BEGINORG":"AGIV","orginal:LBLBGNORG":"Agentschap voor Geografische Informatie Vlaanderen","orginal:TGBEP":1,"orginal:LBLTGBEP":"openbare weg","highway":"unclassified"},"geometry":{"type":"LineString","coordinates":[[2.6619046926498413,51.01591456640253],[2.6619529724121094,51.01593144029721],[2.6628541946411133,51.016154175131675]]}},{"type":"Feature","properties":{"orginal:WS_OIDN":906973,"orginal:WS_UIDN":"906973_1","orginal:WS_GIDN":"906973_1","orginal:B_WK_OIDN":1858646,"orginal:E_WK_OIDN":1823077,"orginal:STATUS":4,"orginal:LBLSTATUS":"in gebruik","orginal:MORF":103,"orginal:LBLMORF":"weg bestaande uit één rijbaan","orginal:WEGCAT":"-8","orginal:LBLWEGCAT":"niet gekend","orginal:LSTRNMID":61438,"orginal:LSTRNM":"Zomerweg","orginal:RSTRNMID":61438,"orginal:RSTRNM":"Zomerweg","orginal:BEHEER":"38025","orginal:LBLBEHEER":"Stad Veurne","orginal:METHODE":2,"orginal:LBLMETHOD":"ingemeten","orginal:OPNDATUM":"20140220T143532","orginal:BEGINTIJD":"20140220T143532","orginal:BEGINORG":"AGIV","orginal:LBLBGNORG":"Agentschap voor Geografische Informatie Vlaanderen","orginal:TGBEP":1,"orginal:LBLTGBEP":"openbare weg","highway":"unclassified"},"geometry":{"type":"LineString","coordinates":[[2.6628541946411133,51.016154175131675],[2.662864923477173,51.016133926554545],[2.6629775762557983,51.016036058307236],[2.6632297039031982,51.01590106728236]]}},{"type":"Feature","properties":{"orginal:WS_OIDN":796857,"orginal:WS_UIDN":"796857_2","orginal:WS_GIDN":"796857_2","orginal:B_WK_OIDN":1593713,"orginal:E_WK_OIDN":1973607,"orginal:STATUS":4,"orginal:LBLSTATUS":"in gebruik","orginal:MORF":103,"orginal:LBLMORF":"weg bestaande uit één rijbaan","orginal:WEGCAT":"L1","orginal:LBLWEGCAT":"lokale weg type 1","orginal:LSTRNMID":61257,"orginal:LSTRNM":"Gouden-Hoofdstraat","orginal:RSTRNMID":61257,"orginal:RSTRNM":"Gouden-Hoofdstraat","orginal:BEHEER":"38025","orginal:LBLBEHEER":"Stad Veurne","orginal:METHODE":2,"orginal:LBLMETHOD":"ingemeten","orginal:OPNDATUM":"20150504T102053","orginal:BEGINTIJD":"20150504T103707","orginal:BEGINORG":"AGIV","orginal:LBLBGNORG":"Agentschap voor Geografische Informatie Vlaanderen","orginal:TGBEP":1,"orginal:LBLTGBEP":"openbare weg","highway":"unclassified"},"geometry":{"type":"LineString","coordinates":[[2.6660406589508057,51.01888765187201],[2.6659172773361206,51.01884040796355],[2.6651716232299805,51.01850632466554],[2.6650160551071167,51.018442207393605],[2.664855122566223,51.01838483923308],[2.664511799812317,51.018283601129525],[2.6641952991485596,51.01820598510045],[2.6639968156814575,51.01817223896035],[2.6633262634277344,51.018027130277915]]}},{"type":"Feature","properties":{"orginal:WS_OIDN":876277,"orginal:WS_UIDN":"876277_1","orginal:WS_GIDN":"876277_1","orginal:B_WK_OIDN":1593713,"orginal:E_WK_OIDN":1743791,"orginal:STATUS":4,"orginal:LBLSTATUS":"in gebruik","orginal:MORF":103,"orginal:LBLMORF":"weg bestaande uit één rijbaan","orginal:WEGCAT":"L1","orginal:LBLWEGCAT":"lokale weg type 1","orginal:LSTRNMID":61257,"orginal:LSTRNM":"Gouden-Hoofdstraat","orginal:RSTRNMID":61257,"orginal:RSTRNM":"Gouden-Hoofdstraat","orginal:BEHEER":"38025","orginal:LBLBEHEER":"Stad Veurne","orginal:METHODE":2,"orginal:LBLMETHOD":"ingemeten","orginal:OPNDATUM":"20140220T143532","orginal:BEGINTIJD":"20140220T143532","orginal:BEGINORG":"ABMV","orginal:LBLBGNORG":"MOW - Afdeling Beleid Mobiliteit en Verkeersveiligheid","orginal:TGBEP":1,"orginal:LBLTGBEP":"openbare weg","highway":"unclassified"},"geometry":{"type":"LineString","coordinates":[[2.6660406589508057,51.01888765187201],[2.6676660776138306,51.019457949540765],[2.668132781982422,51.01960642825628],[2.6682132482528687,51.01963679884406]]}},{"type":"Feature","properties":{"orginal:WS_OIDN":911539,"orginal:WS_UIDN":"911539_1","orginal:WS_GIDN":"911539_1","orginal:B_WK_OIDN":1823077,"orginal:E_WK_OIDN":1742941,"orginal:STATUS":4,"orginal:LBLSTATUS":"in gebruik","orginal:MORF":103,"orginal:LBLMORF":"weg bestaande uit één rijbaan","orginal:WEGCAT":"-8","orginal:LBLWEGCAT":"niet gekend","orginal:LSTRNMID":61438,"orginal:LSTRNM":"Zomerweg","orginal:RSTRNMID":61438,"orginal:RSTRNM":"Zomerweg","orginal:BEHEER":"38025","orginal:LBLBEHEER":"Stad Veurne","orginal:METHODE":2,"orginal:LBLMETHOD":"ingemeten","orginal:OPNDATUM":"20140220T143532","orginal:BEGINTIJD":"20140220T143532","orginal:BEGINORG":"AGIV","orginal:LBLBGNORG":"Agentschap voor Geografische Informatie Vlaanderen","orginal:TGBEP":1,"orginal:LBLTGBEP":"openbare weg","highway":"unclassified"},"geometry":{"type":"LineString","coordinates":[[2.6632297039031982,51.01590106728236],[2.6632940769195557,51.015867319464746],[2.663331627845764,51.01583694640786],[2.664055824279785,51.015091112880555],[2.6645010709762573,51.01461188319803],[2.6646941900253296,51.014382391173854],[2.664983868598938,51.0137546571882],[2.665107250213623,51.01348466146277]]}},{"type":"Feature","properties":{"orginal:WS_OIDN":929327,"orginal:WS_UIDN":"929327_1","orginal:WS_GIDN":"929327_1","orginal:B_WK_OIDN":1905559,"orginal:E_WK_OIDN":1858654,"orginal:STATUS":4,"orginal:LBLSTATUS":"in gebruik","orginal:MORF":103,"orginal:LBLMORF":"weg bestaande uit één rijbaan","orginal:WEGCAT":"-8","orginal:LBLWEGCAT":"niet gekend","orginal:LSTRNMID":61321,"orginal:LSTRNM":"Lobbestraat","orginal:RSTRNMID":61321,"orginal:RSTRNM":"Lobbestraat","orginal:BEHEER":"38025","orginal:LBLBEHEER":"Stad Veurne","orginal:METHODE":2,"orginal:LBLMETHOD":"ingemeten","orginal:OPNDATUM":"20140220T143532","orginal:BEGINTIJD":"20140220T143532","orginal:BEGINORG":"AGIV","orginal:LBLBGNORG":"Agentschap voor Geografische Informatie Vlaanderen","orginal:TGBEP":1,"orginal:LBLTGBEP":"openbare weg","highway":"unclassified"},"geometry":{"type":"LineString","coordinates":[[2.673545479774475,51.027488615519616],[2.673121690750122,51.0273502838902],[2.672751545906067,51.02722207371866],[2.67142653465271,51.02670248149806],[2.671228051185608,51.026628253562535],[2.6710832118988037,51.0265843915447],[2.671002745628357,51.02656077351796],[2.6701927185058594,51.02638532494237],[2.6698333024978638,51.02631784454417],[2.669506072998047,51.02627398223265]]}},{"type":"Feature","properties":{"orginal:WS_OIDN":952780,"orginal:WS_UIDN":"952780_1","orginal:WS_GIDN":"952780_1","orginal:B_WK_OIDN":1905559,"orginal:E_WK_OIDN":1765725,"orginal:STATUS":4,"orginal:LBLSTATUS":"in gebruik","orginal:MORF":103,"orginal:LBLMORF":"weg bestaande uit één rijbaan","orginal:WEGCAT":"-8","orginal:LBLWEGCAT":"niet gekend","orginal:LSTRNMID":61330,"orginal:LSTRNM":"Molendreef","orginal:RSTRNMID":61330,"orginal:RSTRNM":"Molendreef","orginal:BEHEER":"38025","orginal:LBLBEHEER":"Stad Veurne","orginal:METHODE":2,"orginal:LBLMETHOD":"ingemeten","orginal:OPNDATUM":"20140220T143532","orginal:BEGINTIJD":"20140220T143532","orginal:BEGINORG":"AGIV","orginal:LBLBGNORG":"Agentschap voor Geografische Informatie Vlaanderen","orginal:TGBEP":1,"orginal:LBLTGBEP":"openbare weg","highway":"unclassified"},"geometry":{"type":"LineString","coordinates":[[2.673545479774475,51.027488615519616],[2.6736044883728027,51.027421136727554],[2.6736152172088623,51.02740089307079],[2.673620581626892,51.027357031784135],[2.673620581626892,51.02726930908628],[2.673599123954773,51.02715796849992],[2.6735615730285645,51.02705337558427],[2.673545479774475,51.02695553038504],[2.673550844192505,51.02686443294485],[2.6735669374465942,51.02683406709167],[2.6736366748809814,51.026756465376536],[2.673802971839905,51.026624879562604],[2.6740872859954834,51.02643930919021],[2.6742535829544067,51.02634483671525],[2.674376964569092,51.0262469900203]]}},{"type":"Feature","properties":{"orginal:WS_OIDN":871896,"orginal:WS_UIDN":"871896_1","orginal:WS_GIDN":"871896_1","orginal:B_WK_OIDN":1743791,"orginal:E_WK_OIDN":1743792,"orginal:STATUS":4,"orginal:LBLSTATUS":"in gebruik","orginal:MORF":103,"orginal:LBLMORF":"weg bestaande uit één rijbaan","orginal:WEGCAT":"L1","orginal:LBLWEGCAT":"lokale weg type 1","orginal:LSTRNMID":61257,"orginal:LSTRNM":"Gouden-Hoofdstraat","orginal:RSTRNMID":61257,"orginal:RSTRNM":"Gouden-Hoofdstraat","orginal:BEHEER":"38025","orginal:LBLBEHEER":"Stad Veurne","orginal:METHODE":2,"orginal:LBLMETHOD":"ingemeten","orginal:OPNDATUM":"20140220T143532","orginal:BEGINTIJD":"20140220T143532","orginal:BEGINORG":"ABMV","orginal:LBLBGNORG":"MOW - Afdeling Beleid Mobiliteit en Verkeersveiligheid","orginal:TGBEP":1,"orginal:LBLTGBEP":"openbare weg","highway":"unclassified"},"geometry":{"type":"LineString","coordinates":[[2.6682132482528687,51.01963679884406],[2.6685941219329834,51.019792025982014],[2.6697421073913574,51.02033531687229],[2.6700103282928467,51.020473669436],[2.6708847284317017,51.02096633618822],[2.6709651947021484,51.0210270755623],[2.6710671186447144,51.021141805274],[2.6710939407348633,51.02120929320705],[2.6711100339889526,51.02150961331796],[2.6711422204971313,51.02160409564718],[2.671222686767578,51.02169857778384],[2.6713192462921143,51.02177956231915],[2.671528458595276,51.02186392105969],[2.6719844341278076,51.02199214605133],[2.6724404096603394,51.02210349904581],[2.672553062438965,51.02212037068833]]}},{"type":"Feature","properties":{"orginal:WS_OIDN":796858,"orginal:WS_UIDN":"796858_1","orginal:WS_GIDN":"796858_1","orginal:B_WK_OIDN":1711479,"orginal:E_WK_OIDN":445203,"orginal:STATUS":4,"orginal:LBLSTATUS":"in gebruik","orginal:MORF":103,"orginal:LBLMORF":"weg bestaande uit één rijbaan","orginal:WEGCAT":"L1","orginal:LBLWEGCAT":"lokale weg type 1","orginal:LSTRNMID":61257,"orginal:LSTRNM":"Gouden-Hoofdstraat","orginal:RSTRNMID":61257,"orginal:RSTRNM":"Gouden-Hoofdstraat","orginal:BEHEER":"38025","orginal:LBLBEHEER":"Stad Veurne","orginal:METHODE":2,"orginal:LBLMETHOD":"ingemeten","orginal:OPNDATUM":"20140220T143532","orginal:BEGINTIJD":"20140220T143532","orginal:BEGINORG":"ABMV","orginal:LBLBGNORG":"MOW - Afdeling Beleid Mobiliteit en Verkeersveiligheid","orginal:TGBEP":1,"orginal:LBLTGBEP":"openbare weg","highway":"unclassified"},"geometry":{"type":"LineString","coordinates":[[2.675771713256836,51.02272437144529],[2.6753371953964233,51.02262651710822],[2.6746881008148193,51.022494919570676],[2.673245072364807,51.022238472013896]]}},{"type":"Feature","properties":{"orginal:WS_OIDN":796859,"orginal:WS_UIDN":"796859_1","orginal:WS_GIDN":"796859_1","orginal:B_WK_OIDN":445203,"orginal:E_WK_OIDN":1743792,"orginal:STATUS":4,"orginal:LBLSTATUS":"in gebruik","orginal:MORF":103,"orginal:LBLMORF":"weg bestaande uit één rijbaan","orginal:WEGCAT":"L1","orginal:LBLWEGCAT":"lokale weg type 1","orginal:LSTRNMID":61257,"orginal:LSTRNM":"Gouden-Hoofdstraat","orginal:RSTRNMID":61257,"orginal:RSTRNM":"Gouden-Hoofdstraat","orginal:BEHEER":"38025","orginal:LBLBEHEER":"Stad Veurne","orginal:METHODE":2,"orginal:LBLMETHOD":"ingemeten","orginal:OPNDATUM":"20140220T143532","orginal:BEGINTIJD":"20140220T143532","orginal:BEGINORG":"ABMV","orginal:LBLBGNORG":"MOW - Afdeling Beleid Mobiliteit en Verkeersveiligheid","orginal:TGBEP":1,"orginal:LBLTGBEP":"openbare weg","highway":"unclassified"},"geometry":{"type":"LineString","coordinates":[[2.673245072364807,51.022238472013896],[2.672553062438965,51.02212037068833]]}},{"type":"Feature","properties":{"orginal:WS_OIDN":882863,"orginal:WS_UIDN":"882863_1","orginal:WS_GIDN":"882863_1","orginal:B_WK_OIDN":1765725,"orginal:E_WK_OIDN":1711480,"orginal:STATUS":4,"orginal:LBLSTATUS":"in gebruik","orginal:MORF":103,"orginal:LBLMORF":"weg bestaande uit één rijbaan","orginal:WEGCAT":"-8","orginal:LBLWEGCAT":"niet gekend","orginal:LSTRNMID":61330,"orginal:LSTRNM":"Molendreef","orginal:RSTRNMID":61330,"orginal:RSTRNM":"Molendreef","orginal:BEHEER":"38025","orginal:LBLBEHEER":"Stad Veurne","orginal:METHODE":2,"orginal:LBLMETHOD":"ingemeten","orginal:OPNDATUM":"20140220T143532","orginal:BEGINTIJD":"20140220T143532","orginal:BEGINORG":"AGIV","orginal:LBLBGNORG":"Agentschap voor Geografische Informatie Vlaanderen","orginal:TGBEP":1,"orginal:LBLTGBEP":"openbare weg","highway":"unclassified"},"geometry":{"type":"LineString","coordinates":[[2.674376964569092,51.0262469900203],[2.67467200756073,51.02597706703253],[2.675101161003113,51.02562616479861],[2.67517626285553,51.02554181290404],[2.675272822380066,51.025400101375624],[2.675449848175049,51.02499183478855],[2.6757556200027466,51.02455657140908],[2.6758575439453125,51.02443172767005],[2.6759755611419678,51.02435074776764],[2.6761525869369507,51.02425627103608],[2.676222324371338,51.024209032598066],[2.676270604133606,51.02416854247005],[2.6763027906417847,51.02412805230665],[2.6763778924942017,51.024020078364714],[2.6769250631332397,51.022990939108894]]}},{"type":"Feature","properties":{"orginal:WS_OIDN":879721,"orginal:WS_UIDN":"879721_2","orginal:WS_GIDN":"879721_2","orginal:B_WK_OIDN":1759441,"orginal:E_WK_OIDN":1725585,"orginal:STATUS":4,"orginal:LBLSTATUS":"in gebruik","orginal:MORF":103,"orginal:LBLMORF":"weg bestaande uit één rijbaan","orginal:WEGCAT":"S1","orginal:LBLWEGCAT":"secundaire weg type 1","orginal:LSTRNMID":61282,"orginal:LSTRNM":"Ieperse Steenweg","orginal:RSTRNMID":61282,"orginal:RSTRNM":"Ieperse Steenweg","orginal:BEHEER":"AWV315","orginal:LBLBEHEER":"Agentschap Wegen en Verkeer - District Oostende","orginal:METHODE":2,"orginal:LBLMETHOD":"ingemeten","orginal:OPNDATUM":"20161012T132044","orginal:BEGINTIJD":"20161012T134046","orginal:BEGINORG":"AWV","orginal:LBLBGNORG":"Agentschap Wegen en Verkeer","orginal:TGBEP":1,"orginal:LBLTGBEP":"openbare weg","highway":"unclassified"},"geometry":{"type":"LineString","coordinates":[[2.678362727165222,51.0254169718184],[2.678491473197937,51.02497833831103]]}},{"type":"Feature","properties":{"orginal:WS_OIDN":857744,"orginal:WS_UIDN":"857744_2","orginal:WS_GIDN":"857744_2","orginal:B_WK_OIDN":1725585,"orginal:E_WK_OIDN":1589251,"orginal:STATUS":4,"orginal:LBLSTATUS":"in gebruik","orginal:MORF":102,"orginal:LBLMORF":"weg met gescheiden rijbanen die geen autosnelweg is","orginal:WEGCAT":"S1","orginal:LBLWEGCAT":"secundaire weg type 1","orginal:LSTRNMID":61282,"orginal:LSTRNM":"Ieperse Steenweg","orginal:RSTRNMID":61282,"orginal:RSTRNM":"Ieperse Steenweg","orginal:BEHEER":"AWV315","orginal:LBLBEHEER":"Agentschap Wegen en Verkeer - District Oostende","orginal:METHODE":2,"orginal:LBLMETHOD":"ingemeten","orginal:OPNDATUM":"20161012T132044","orginal:BEGINTIJD":"20161012T134046","orginal:BEGINORG":"AWV","orginal:LBLBGNORG":"Agentschap Wegen en Verkeer","orginal:TGBEP":1,"orginal:LBLTGBEP":"openbare weg","highway":"unclassified"},"geometry":{"type":"LineString","coordinates":[[2.678491473197937,51.02497833831103],[2.6785343885421753,51.02492435236175],[2.6788026094436646,51.02416854247005],[2.6789313554763794,51.02371640030469],[2.6790064573287964,51.02349370179638]]}},{"type":"Feature","properties":{"orginal:WS_OIDN":862793,"orginal:WS_UIDN":"862793_2","orginal:WS_GIDN":"862793_2","orginal:B_WK_OIDN":1725585,"orginal:E_WK_OIDN":1593720,"orginal:STATUS":4,"orginal:LBLSTATUS":"in gebruik","orginal:MORF":102,"orginal:LBLMORF":"weg met gescheiden rijbanen die geen autosnelweg is","orginal:WEGCAT":"S1","orginal:LBLWEGCAT":"secundaire weg type 1","orginal:LSTRNMID":61282,"orginal:LSTRNM":"Ieperse Steenweg","orginal:RSTRNMID":61282,"orginal:RSTRNM":"Ieperse Steenweg","orginal:BEHEER":"AWV315","orginal:LBLBEHEER":"Agentschap Wegen en Verkeer - District Oostende","orginal:METHODE":2,"orginal:LBLMETHOD":"ingemeten","orginal:OPNDATUM":"20161012T132044","orginal:BEGINTIJD":"20161012T134046","orginal:BEGINORG":"AWV","orginal:LBLBGNORG":"Agentschap Wegen en Verkeer","orginal:TGBEP":1,"orginal:LBLTGBEP":"openbare weg","highway":"unclassified"},"geometry":{"type":"LineString","coordinates":[[2.678491473197937,51.02497833831103],[2.678491473197937,51.02490748173972],[2.6785504817962646,51.02465779581553],[2.678641676902771,51.02418541336104],[2.678861618041992,51.023463333735066]]}},{"type":"Feature","properties":{"orginal:WS_OIDN":855740,"orginal:WS_UIDN":"855740_1","orginal:WS_GIDN":"855740_1","orginal:B_WK_OIDN":1711479,"orginal:E_WK_OIDN":1711480,"orginal:STATUS":4,"orginal:LBLSTATUS":"in gebruik","orginal:MORF":103,"orginal:LBLMORF":"weg bestaande uit één rijbaan","orginal:WEGCAT":"L1","orginal:LBLWEGCAT":"lokale weg type 1","orginal:LSTRNMID":61257,"orginal:LSTRNM":"Gouden-Hoofdstraat","orginal:RSTRNMID":61257,"orginal:RSTRNM":"Gouden-Hoofdstraat","orginal:BEHEER":"38025","orginal:LBLBEHEER":"Stad Veurne","orginal:METHODE":2,"orginal:LBLMETHOD":"ingemeten","orginal:OPNDATUM":"20140220T143532","orginal:BEGINTIJD":"20140220T143532","orginal:BEGINORG":"ABMV","orginal:LBLBGNORG":"MOW - Afdeling Beleid Mobiliteit en Verkeersveiligheid","orginal:TGBEP":1,"orginal:LBLTGBEP":"openbare weg","highway":"unclassified"},"geometry":{"type":"LineString","coordinates":[[2.675771713256836,51.02272437144529],[2.6769250631332397,51.022990939108894]]}},{"type":"Feature","properties":{"orginal:WS_OIDN":796860,"orginal:WS_UIDN":"796860_1","orginal:WS_GIDN":"796860_1","orginal:B_WK_OIDN":1711480,"orginal:E_WK_OIDN":1593720,"orginal:STATUS":4,"orginal:LBLSTATUS":"in gebruik","orginal:MORF":103,"orginal:LBLMORF":"weg bestaande uit één rijbaan","orginal:WEGCAT":"L1","orginal:LBLWEGCAT":"lokale weg type 1","orginal:LSTRNMID":61257,"orginal:LSTRNM":"Gouden-Hoofdstraat","orginal:RSTRNMID":61257,"orginal:RSTRNM":"Gouden-Hoofdstraat","orginal:BEHEER":"38025","orginal:LBLBEHEER":"Stad Veurne","orginal:METHODE":2,"orginal:LBLMETHOD":"ingemeten","orginal:OPNDATUM":"20140220T143532","orginal:BEGINTIJD":"20140220T143532","orginal:BEGINORG":"ABMV","orginal:LBLBGNORG":"MOW - Afdeling Beleid Mobiliteit en Verkeersveiligheid","orginal:TGBEP":1,"orginal:LBLTGBEP":"openbare weg","highway":"unclassified"},"geometry":{"type":"LineString","coordinates":[[2.6769250631332397,51.022990939108894],[2.6782983541488647,51.023335112812504],[2.678861618041992,51.023463333735066]]}},{"type":"Feature","properties":{"orginal:WS_OIDN":911548,"orginal:WS_UIDN":"911548_1","orginal:WS_GIDN":"911548_1","orginal:B_WK_OIDN":1711479,"orginal:E_WK_OIDN":1680385,"orginal:STATUS":4,"orginal:LBLSTATUS":"in gebruik","orginal:MORF":103,"orginal:LBLMORF":"weg bestaande uit één rijbaan","orginal:WEGCAT":"-8","orginal:LBLWEGCAT":"niet gekend","orginal:LSTRNMID":61447,"orginal:LSTRNM":"Zwart-Paardstraat","orginal:RSTRNMID":61447,"orginal:RSTRNM":"Zwart-Paardstraat","orginal:BEHEER":"38025","orginal:LBLBEHEER":"Stad Veurne","orginal:METHODE":2,"orginal:LBLMETHOD":"ingemeten","orginal:OPNDATUM":"20140220T143532","orginal:BEGINTIJD":"20140220T143532","orginal:BEGINORG":"AGIV","orginal:LBLBGNORG":"Agentschap voor Geografische Informatie Vlaanderen","orginal:TGBEP":1,"orginal:LBLTGBEP":"openbare weg","highway":"unclassified"},"geometry":{"type":"LineString","coordinates":[[2.675771713256836,51.02272437144529],[2.6760131120681763,51.022363321659526],[2.6761794090270996,51.022137242324675],[2.676538825035095,51.02161421874246],[2.677064538002014,51.02097645942274],[2.677241563796997,51.020746998897124],[2.6775097846984863,51.02032856795617],[2.6779335737228394,51.01983589442679],[2.678217887878418,51.01943432788309],[2.6782983541488647,51.019268975942396]]}},{"type":"Feature","properties":{"orginal:WS_OIDN":932942,"orginal:WS_UIDN":"932942_2","orginal:WS_GIDN":"932942_2","orginal:B_WK_OIDN":1593720,"orginal:E_WK_OIDN":1589251,"orginal:STATUS":4,"orginal:LBLSTATUS":"in gebruik","orginal:MORF":103,"orginal:LBLMORF":"weg bestaande uit één rijbaan","orginal:WEGCAT":"L1","orginal:LBLWEGCAT":"lokale weg type 1","orginal:LSTRNMID":61341,"orginal:LSTRNM":"Oerenstraat","orginal:RSTRNMID":61341,"orginal:RSTRNM":"Oerenstraat","orginal:BEHEER":"AWV315","orginal:LBLBEHEER":"Agentschap Wegen en Verkeer - District Oostende","orginal:METHODE":2,"orginal:LBLMETHOD":"ingemeten","orginal:OPNDATUM":"20161012T132044","orginal:BEGINTIJD":"20161012T134046","orginal:BEGINORG":"AWV","orginal:LBLBGNORG":"Agentschap Wegen en Verkeer","orginal:TGBEP":1,"orginal:LBLTGBEP":"openbare weg","highway":"unclassified"},"geometry":{"type":"LineString","coordinates":[[2.678861618041992,51.023463333735066],[2.6790064573287964,51.02349370179638]]}},{"type":"Feature","properties":{"orginal:WS_OIDN":888069,"orginal:WS_UIDN":"888069_2","orginal:WS_GIDN":"888069_2","orginal:B_WK_OIDN":1593720,"orginal:E_WK_OIDN":1776138,"orginal:STATUS":4,"orginal:LBLSTATUS":"in gebruik","orginal:MORF":102,"orginal:LBLMORF":"weg met gescheiden rijbanen die geen autosnelweg is","orginal:WEGCAT":"S1","orginal:LBLWEGCAT":"secundaire weg type 1","orginal:LSTRNMID":61282,"orginal:LSTRNM":"Ieperse Steenweg","orginal:RSTRNMID":61282,"orginal:RSTRNM":"Ieperse Steenweg","orginal:BEHEER":"AWV315","orginal:LBLBEHEER":"Agentschap Wegen en Verkeer - District Oostende","orginal:METHODE":2,"orginal:LBLMETHOD":"ingemeten","orginal:OPNDATUM":"20161012T132044","orginal:BEGINTIJD":"20161012T134046","orginal:BEGINORG":"AWV","orginal:LBLBGNORG":"Agentschap Wegen en Verkeer","orginal:TGBEP":1,"orginal:LBLTGBEP":"openbare weg","highway":"unclassified"},"geometry":{"type":"LineString","coordinates":[[2.678861618041992,51.023463333735066],[2.679011821746826,51.02294032511347]]}},{"type":"Feature","properties":{"orginal:WS_OIDN":947046,"orginal:WS_UIDN":"947046_2","orginal:WS_GIDN":"947046_2","orginal:B_WK_OIDN":1589251,"orginal:E_WK_OIDN":1894092,"orginal:STATUS":4,"orginal:LBLSTATUS":"in gebruik","orginal:MORF":102,"orginal:LBLMORF":"weg met gescheiden rijbanen die geen autosnelweg is","orginal:WEGCAT":"S1","orginal:LBLWEGCAT":"secundaire weg type 1","orginal:LSTRNMID":61282,"orginal:LSTRNM":"Ieperse Steenweg","orginal:RSTRNMID":61282,"orginal:RSTRNM":"Ieperse Steenweg","orginal:BEHEER":"AWV315","orginal:LBLBEHEER":"Agentschap Wegen en Verkeer - District Oostende","orginal:METHODE":2,"orginal:LBLMETHOD":"ingemeten","orginal:OPNDATUM":"20161012T132044","orginal:BEGINTIJD":"20161012T134046","orginal:BEGINORG":"AWV","orginal:LBLBGNORG":"Agentschap Wegen en Verkeer","orginal:TGBEP":1,"orginal:LBLTGBEP":"openbare weg","highway":"unclassified"},"geometry":{"type":"LineString","coordinates":[[2.6790064573287964,51.02349370179638],[2.6791781187057495,51.022963944984866]]}},{"type":"Feature","properties":{"orginal:WS_OIDN":856933,"orginal:WS_UIDN":"856933_3","orginal:WS_GIDN":"856933_3","orginal:B_WK_OIDN":1776138,"orginal:E_WK_OIDN":1894092,"orginal:STATUS":4,"orginal:LBLSTATUS":"in gebruik","orginal:MORF":103,"orginal:LBLMORF":"weg bestaande uit één rijbaan","orginal:WEGCAT":"-9","orginal:LBLWEGCAT":"niet van toepassing","orginal:LSTRNMID":61282,"orginal:LSTRNM":"Ieperse Steenweg","orginal:RSTRNMID":61282,"orginal:RSTRNM":"Ieperse Steenweg","orginal:BEHEER":"AWV315","orginal:LBLBEHEER":"Agentschap Wegen en Verkeer - District Oostende","orginal:METHODE":2,"orginal:LBLMETHOD":"ingemeten","orginal:OPNDATUM":"20170309T101255","orginal:BEGINTIJD":"20170309T104253","orginal:BEGINORG":"AWV","orginal:LBLBGNORG":"Agentschap Wegen en Verkeer","orginal:TGBEP":1,"orginal:LBLTGBEP":"openbare weg","highway":"unclassified"},"geometry":{"type":"LineString","coordinates":[[2.679011821746826,51.02294032511347],[2.6791781187057495,51.022963944984866]]}},{"type":"Feature","properties":{"orginal:WS_OIDN":873435,"orginal:WS_UIDN":"873435_2","orginal:WS_GIDN":"873435_2","orginal:B_WK_OIDN":1776138,"orginal:E_WK_OIDN":1742623,"orginal:STATUS":4,"orginal:LBLSTATUS":"in gebruik","orginal:MORF":102,"orginal:LBLMORF":"weg met gescheiden rijbanen die geen autosnelweg is","orginal:WEGCAT":"S1","orginal:LBLWEGCAT":"secundaire weg type 1","orginal:LSTRNMID":61282,"orginal:LSTRNM":"Ieperse Steenweg","orginal:RSTRNMID":61282,"orginal:RSTRNM":"Ieperse Steenweg","orginal:BEHEER":"AWV315","orginal:LBLBEHEER":"Agentschap Wegen en Verkeer - District Oostende","orginal:METHODE":2,"orginal:LBLMETHOD":"ingemeten","orginal:OPNDATUM":"20161012T132044","orginal:BEGINTIJD":"20161012T134046","orginal:BEGINORG":"AWV","orginal:LBLBGNORG":"Agentschap Wegen en Verkeer","orginal:TGBEP":1,"orginal:LBLTGBEP":"openbare weg","highway":"unclassified"},"geometry":{"type":"LineString","coordinates":[[2.679011821746826,51.02294032511347],[2.6790815591812134,51.02269062859378],[2.679113745689392,51.02260289706487]]}},{"type":"Feature","properties":{"orginal:WS_OIDN":887618,"orginal:WS_UIDN":"887618_2","orginal:WS_GIDN":"887618_2","orginal:B_WK_OIDN":1894092,"orginal:E_WK_OIDN":1775236,"orginal:STATUS":4,"orginal:LBLSTATUS":"in gebruik","orginal:MORF":102,"orginal:LBLMORF":"weg met gescheiden rijbanen die geen autosnelweg is","orginal:WEGCAT":"S1","orginal:LBLWEGCAT":"secundaire weg type 1","orginal:LSTRNMID":61282,"orginal:LSTRNM":"Ieperse Steenweg","orginal:RSTRNMID":61282,"orginal:RSTRNM":"Ieperse Steenweg","orginal:BEHEER":"AWV315","orginal:LBLBEHEER":"Agentschap Wegen en Verkeer - District Oostende","orginal:METHODE":2,"orginal:LBLMETHOD":"ingemeten","orginal:OPNDATUM":"20161012T132044","orginal:BEGINTIJD":"20161012T134046","orginal:BEGINORG":"AWV","orginal:LBLBGNORG":"Agentschap Wegen en Verkeer","orginal:TGBEP":1,"orginal:LBLTGBEP":"openbare weg","highway":"unclassified"},"geometry":{"type":"LineString","coordinates":[[2.6791781187057495,51.022963944984866],[2.6792746782302856,51.022623142817054]]}},{"type":"Feature","properties":{"orginal:WS_OIDN":871312,"orginal:WS_UIDN":"871312_3","orginal:WS_GIDN":"871312_3","orginal:B_WK_OIDN":1742623,"orginal:E_WK_OIDN":1775236,"orginal:STATUS":4,"orginal:LBLSTATUS":"in gebruik","orginal:MORF":103,"orginal:LBLMORF":"weg bestaande uit één rijbaan","orginal:WEGCAT":"-9","orginal:LBLWEGCAT":"niet van toepassing","orginal:LSTRNMID":61282,"orginal:LSTRNM":"Ieperse Steenweg","orginal:RSTRNMID":61282,"orginal:RSTRNM":"Ieperse Steenweg","orginal:BEHEER":"AWV315","orginal:LBLBEHEER":"Agentschap Wegen en Verkeer - District Oostende","orginal:METHODE":2,"orginal:LBLMETHOD":"ingemeten","orginal:OPNDATUM":"20170309T101255","orginal:BEGINTIJD":"20170309T104253","orginal:BEGINORG":"AWV","orginal:LBLBGNORG":"Agentschap Wegen en Verkeer","orginal:TGBEP":1,"orginal:LBLTGBEP":"openbare weg","highway":"unclassified"},"geometry":{"type":"LineString","coordinates":[[2.679113745689392,51.02260289706487],[2.6792746782302856,51.022623142817054]]}},{"type":"Feature","properties":{"orginal:WS_OIDN":953923,"orginal:WS_UIDN":"953923_2","orginal:WS_GIDN":"953923_2","orginal:B_WK_OIDN":1759452,"orginal:E_WK_OIDN":1775236,"orginal:STATUS":4,"orginal:LBLSTATUS":"in gebruik","orginal:MORF":102,"orginal:LBLMORF":"weg met gescheiden rijbanen die geen autosnelweg is","orginal:WEGCAT":"S1","orginal:LBLWEGCAT":"secundaire weg type 1","orginal:LSTRNMID":61282,"orginal:LSTRNM":"Ieperse Steenweg","orginal:RSTRNMID":61282,"orginal:RSTRNM":"Ieperse Steenweg","orginal:BEHEER":"AWV315","orginal:LBLBEHEER":"Agentschap Wegen en Verkeer - District Oostende","orginal:METHODE":2,"orginal:LBLMETHOD":"ingemeten","orginal:OPNDATUM":"20161012T132044","orginal:BEGINTIJD":"20161012T134046","orginal:BEGINORG":"AWV","orginal:LBLBGNORG":"Agentschap Wegen en Verkeer","orginal:TGBEP":1,"orginal:LBLTGBEP":"openbare weg","highway":"unclassified"},"geometry":{"type":"LineString","coordinates":[[2.6793068647384644,51.0223835675163],[2.679263949394226,51.0225556569421],[2.6792746782302856,51.022623142817054]]}},{"type":"Feature","properties":{"orginal:WS_OIDN":969715,"orginal:WS_UIDN":"969715_2","orginal:WS_GIDN":"969715_2","orginal:B_WK_OIDN":1742623,"orginal:E_WK_OIDN":1678455,"orginal:STATUS":4,"orginal:LBLSTATUS":"in gebruik","orginal:MORF":102,"orginal:LBLMORF":"weg met gescheiden rijbanen die geen autosnelweg is","orginal:WEGCAT":"S1","orginal:LBLWEGCAT":"secundaire weg type 1","orginal:LSTRNMID":61282,"orginal:LSTRNM":"Ieperse Steenweg","orginal:RSTRNMID":61282,"orginal:RSTRNM":"Ieperse Steenweg","orginal:BEHEER":"AWV315","orginal:LBLBEHEER":"Agentschap Wegen en Verkeer - District Oostende","orginal:METHODE":2,"orginal:LBLMETHOD":"ingemeten","orginal:OPNDATUM":"20161012T132044","orginal:BEGINTIJD":"20161012T134046","orginal:BEGINORG":"AWV","orginal:LBLBGNORG":"Agentschap Wegen en Verkeer","orginal:TGBEP":1,"orginal:LBLTGBEP":"openbare weg","highway":"unclassified"},"geometry":{"type":"LineString","coordinates":[[2.679113745689392,51.02260289706487],[2.679215669631958,51.022370070279436]]}},{"type":"Feature","properties":{"orginal:WS_OIDN":794626,"orginal:WS_UIDN":"794626_1","orginal:WS_GIDN":"794626_1","orginal:B_WK_OIDN":1589251,"orginal:E_WK_OIDN":1622881,"orginal:STATUS":4,"orginal:LBLSTATUS":"in gebruik","orginal:MORF":103,"orginal:LBLMORF":"weg bestaande uit één rijbaan","orginal:WEGCAT":"L2","orginal:LBLWEGCAT":"lokale weg type 2","orginal:LSTRNMID":61341,"orginal:LSTRNM":"Oerenstraat","orginal:RSTRNMID":61341,"orginal:RSTRNM":"Oerenstraat","orginal:BEHEER":"38025","orginal:LBLBEHEER":"Stad Veurne","orginal:METHODE":2,"orginal:LBLMETHOD":"ingemeten","orginal:OPNDATUM":"20140220T143532","orginal:BEGINTIJD":"20140220T143532","orginal:BEGINORG":"ABMV","orginal:LBLBGNORG":"MOW - Afdeling Beleid Mobiliteit en Verkeersveiligheid","orginal:TGBEP":1,"orginal:LBLTGBEP":"openbare weg","highway":"unclassified"},"geometry":{"type":"LineString","coordinates":[[2.6790064573287964,51.02349370179638],[2.6806640625,51.02386149118158],[2.6808303594589233,51.023895233180866],[2.681093215942383,51.02397621387897]]}},{"type":"Feature","properties":{"orginal:WS_OIDN":839228,"orginal:WS_UIDN":"839228_2","orginal:WS_GIDN":"839228_2","orginal:B_WK_OIDN":1678455,"orginal:E_WK_OIDN":1678456,"orginal:STATUS":4,"orginal:LBLSTATUS":"in gebruik","orginal:MORF":102,"orginal:LBLMORF":"weg met gescheiden rijbanen die geen autosnelweg is","orginal:WEGCAT":"S1","orginal:LBLWEGCAT":"secundaire weg type 1","orginal:LSTRNMID":61282,"orginal:LSTRNM":"Ieperse Steenweg","orginal:RSTRNMID":61282,"orginal:RSTRNM":"Ieperse Steenweg","orginal:BEHEER":"AWV315","orginal:LBLBEHEER":"Agentschap Wegen en Verkeer - District Oostende","orginal:METHODE":2,"orginal:LBLMETHOD":"ingemeten","orginal:OPNDATUM":"20161012T132044","orginal:BEGINTIJD":"20161012T134046","orginal:BEGINORG":"AWV","orginal:LBLBGNORG":"Agentschap Wegen en Verkeer","orginal:TGBEP":1,"orginal:LBLTGBEP":"openbare weg","highway":"unclassified"},"geometry":{"type":"LineString","coordinates":[[2.679215669631958,51.022370070279436],[2.679263949394226,51.022235097694505]]}},{"type":"Feature","properties":{"orginal:WS_OIDN":879726,"orginal:WS_UIDN":"879726_2","orginal:WS_GIDN":"879726_2","orginal:B_WK_OIDN":1759451,"orginal:E_WK_OIDN":1759452,"orginal:STATUS":4,"orginal:LBLSTATUS":"in gebruik","orginal:MORF":102,"orginal:LBLMORF":"weg met gescheiden rijbanen die geen autosnelweg is","orginal:WEGCAT":"S1","orginal:LBLWEGCAT":"secundaire weg type 1","orginal:LSTRNMID":61282,"orginal:LSTRNM":"Ieperse Steenweg","orginal:RSTRNMID":61282,"orginal:RSTRNM":"Ieperse Steenweg","orginal:BEHEER":"AWV315","orginal:LBLBEHEER":"Agentschap Wegen en Verkeer - District Oostende","orginal:METHODE":2,"orginal:LBLMETHOD":"ingemeten","orginal:OPNDATUM":"20161012T132044","orginal:BEGINTIJD":"20161012T134046","orginal:BEGINORG":"AWV","orginal:LBLBGNORG":"Agentschap Wegen en Verkeer","orginal:TGBEP":1,"orginal:LBLTGBEP":"openbare weg","highway":"unclassified"},"geometry":{"type":"LineString","coordinates":[[2.679339051246643,51.022245220651996],[2.6793068647384644,51.0223835675163]]}},{"type":"Feature","properties":{"orginal:WS_OIDN":873246,"orginal:WS_UIDN":"873246_2","orginal:WS_GIDN":"873246_2","orginal:B_WK_OIDN":1678456,"orginal:E_WK_OIDN":1746492,"orginal:STATUS":4,"orginal:LBLSTATUS":"in gebruik","orginal:MORF":102,"orginal:LBLMORF":"weg met gescheiden rijbanen die geen autosnelweg is","orginal:WEGCAT":"S1","orginal:LBLWEGCAT":"secundaire weg type 1","orginal:LSTRNMID":61282,"orginal:LSTRNM":"Ieperse Steenweg","orginal:RSTRNMID":61282,"orginal:RSTRNM":"Ieperse Steenweg","orginal:BEHEER":"AWV315","orginal:LBLBEHEER":"Agentschap Wegen en Verkeer - District Oostende","orginal:METHODE":2,"orginal:LBLMETHOD":"ingemeten","orginal:OPNDATUM":"20161012T132044","orginal:BEGINTIJD":"20161012T134046","orginal:BEGINORG":"AWV","orginal:LBLBGNORG":"Agentschap Wegen en Verkeer","orginal:TGBEP":1,"orginal:LBLTGBEP":"openbare weg","highway":"unclassified"},"geometry":{"type":"LineString","coordinates":[[2.679263949394226,51.022235097694505],[2.6793283224105835,51.02204950974857],[2.679360508918762,51.02202926374588]]}},{"type":"Feature","properties":{"orginal:WS_OIDN":858708,"orginal:WS_UIDN":"858708_2","orginal:WS_GIDN":"858708_2","orginal:B_WK_OIDN":1746492,"orginal:E_WK_OIDN":1759451,"orginal:STATUS":4,"orginal:LBLSTATUS":"in gebruik","orginal:MORF":102,"orginal:LBLMORF":"weg met gescheiden rijbanen die geen autosnelweg is","orginal:WEGCAT":"S1","orginal:LBLWEGCAT":"secundaire weg type 1","orginal:LSTRNMID":61282,"orginal:LSTRNM":"Ieperse Steenweg","orginal:RSTRNMID":61282,"orginal:RSTRNM":"Ieperse Steenweg","orginal:BEHEER":"AWV315","orginal:LBLBEHEER":"Agentschap Wegen en Verkeer - District Oostende","orginal:METHODE":2,"orginal:LBLMETHOD":"ingemeten","orginal:OPNDATUM":"20161012T132044","orginal:BEGINTIJD":"20161012T134046","orginal:BEGINORG":"AWV","orginal:LBLBGNORG":"Agentschap Wegen en Verkeer","orginal:TGBEP":1,"orginal:LBLTGBEP":"openbare weg","highway":"unclassified"},"geometry":{"type":"LineString","coordinates":[[2.679360508918762,51.02202926374588],[2.6793712377548218,51.02207987873601],[2.679339051246643,51.022245220651996]]}},{"type":"Feature","properties":{"orginal:WS_OIDN":969720,"orginal:WS_UIDN":"969720_2","orginal:WS_GIDN":"969720_2","orginal:B_WK_OIDN":1587236,"orginal:E_WK_OIDN":1746492,"orginal:STATUS":4,"orginal:LBLSTATUS":"in gebruik","orginal:MORF":103,"orginal:LBLMORF":"weg bestaande uit één rijbaan","orginal:WEGCAT":"S1","orginal:LBLWEGCAT":"secundaire weg type 1","orginal:LSTRNMID":61282,"orginal:LSTRNM":"Ieperse Steenweg","orginal:RSTRNMID":61282,"orginal:RSTRNM":"Ieperse Steenweg","orginal:BEHEER":"AWV315","orginal:LBLBEHEER":"Agentschap Wegen en Verkeer - District Oostende","orginal:METHODE":2,"orginal:LBLMETHOD":"ingemeten","orginal:OPNDATUM":"20161012T132044","orginal:BEGINTIJD":"20161012T134046","orginal:BEGINORG":"AWV","orginal:LBLBGNORG":"Agentschap Wegen en Verkeer","orginal:TGBEP":1,"orginal:LBLTGBEP":"openbare weg","highway":"unclassified"},"geometry":{"type":"LineString","coordinates":[[2.6794034242630005,51.02187404409824],[2.679360508918762,51.02202926374588]]}},{"type":"Feature","properties":{"orginal:WS_OIDN":793618,"orginal:WS_UIDN":"793618_2","orginal:WS_GIDN":"793618_2","orginal:B_WK_OIDN":1587234,"orginal:E_WK_OIDN":1587236,"orginal:STATUS":4,"orginal:LBLSTATUS":"in gebruik","orginal:MORF":103,"orginal:LBLMORF":"weg bestaande uit één rijbaan","orginal:WEGCAT":"S1","orginal:LBLWEGCAT":"secundaire weg type 1","orginal:LSTRNMID":61282,"orginal:LSTRNM":"Ieperse Steenweg","orginal:RSTRNMID":61282,"orginal:RSTRNM":"Ieperse Steenweg","orginal:BEHEER":"AWV315","orginal:LBLBEHEER":"Agentschap Wegen en Verkeer - District Oostende","orginal:METHODE":2,"orginal:LBLMETHOD":"ingemeten","orginal:OPNDATUM":"20161012T132044","orginal:BEGINTIJD":"20161012T134046","orginal:BEGINORG":"AWV","orginal:LBLBGNORG":"Agentschap Wegen en Verkeer","orginal:TGBEP":1,"orginal:LBLTGBEP":"openbare weg","highway":"unclassified"},"geometry":{"type":"LineString","coordinates":[[2.680014967918396,51.019792025982014],[2.6794034242630005,51.02187404409824]]}},{"type":"Feature","properties":{"orginal:WS_OIDN":970547,"orginal:WS_UIDN":"970547_1","orginal:WS_GIDN":"970547_1","orginal:B_WK_OIDN":1743791,"orginal:E_WK_OIDN":1748349,"orginal:STATUS":4,"orginal:LBLSTATUS":"in gebruik","orginal:MORF":103,"orginal:LBLMORF":"weg bestaande uit één rijbaan","orginal:WEGCAT":"-8","orginal:LBLWEGCAT":"niet gekend","orginal:LSTRNMID":61384,"orginal:LSTRNM":"Schaapstraat","orginal:RSTRNMID":61384,"orginal:RSTRNM":"Schaapstraat","orginal:BEHEER":"38025","orginal:LBLBEHEER":"Stad Veurne","orginal:METHODE":2,"orginal:LBLMETHOD":"ingemeten","orginal:OPNDATUM":"20140220T143532","orginal:BEGINTIJD":"20140220T143532","orginal:BEGINORG":"AGIV","orginal:LBLBGNORG":"Agentschap voor Geografische Informatie Vlaanderen","orginal:TGBEP":1,"orginal:LBLTGBEP":"openbare weg","highway":"unclassified"},"geometry":{"type":"LineString","coordinates":[[2.6682132482528687,51.01963679884406],[2.6684653759002686,51.01941070621339],[2.6689106225967407,51.01889777556045],[2.6694899797439575,51.0183173471886],[2.6695597171783447,51.01823973121603],[2.6696187257766724,51.01816548972937],[2.669827938079834,51.01784490012656],[2.669897675514221,51.017753784782315],[2.6700693368911743,51.01755130559849],[2.6703590154647827,51.01724758516494],[2.6707184314727783,51.016906740976026],[2.671077847480774,51.01660301632046],[2.6712602376937866,51.01639715736721],[2.6714909076690674,51.01618117322067],[2.6721882820129395,51.01565808244726],[2.6725906133651733,51.015334100686545],[2.67267107963562,51.01530035245631],[2.672724723815918,51.015293602807304],[2.6727837324142456,51.01529697763192],[2.6729178428649902,51.01532735104246],[2.6740604639053345,51.015735702741324],[2.6743125915527344,51.01581669769226],[2.6745647192001343,51.01588419337662],[2.674945592880249,51.01596856284394],[2.6750367879867554,51.01598206194444],[2.675074338912964,51.01598206194444],[2.675117254257202,51.01596856284394]]}},{"type":"Feature","properties":{"orginal:WS_OIDN":858714,"orginal:WS_UIDN":"858714_1","orginal:WS_GIDN":"858714_1","orginal:B_WK_OIDN":1680385,"orginal:E_WK_OIDN":1587233,"orginal:STATUS":4,"orginal:LBLSTATUS":"in gebruik","orginal:MORF":103,"orginal:LBLMORF":"weg bestaande uit één rijbaan","orginal:WEGCAT":"-8","orginal:LBLWEGCAT":"niet gekend","orginal:LSTRNMID":61282,"orginal:LSTRNM":"Ieperse Steenweg","orginal:RSTRNMID":61282,"orginal:RSTRNM":"Ieperse Steenweg","orginal:BEHEER":"38025","orginal:LBLBEHEER":"Stad Veurne","orginal:METHODE":2,"orginal:LBLMETHOD":"ingemeten","orginal:OPNDATUM":"20140220T143532","orginal:BEGINTIJD":"20140220T143532","orginal:BEGINORG":"AGIV","orginal:LBLBGNORG":"Agentschap voor Geografische Informatie Vlaanderen","orginal:TGBEP":1,"orginal:LBLTGBEP":"openbare weg","highway":"unclassified"},"geometry":{"type":"LineString","coordinates":[[2.6782983541488647,51.019268975942396],[2.680036425590515,51.01971441247798]]}},{"type":"Feature","properties":{"orginal:WS_OIDN":793617,"orginal:WS_UIDN":"793617_2","orginal:WS_GIDN":"793617_2","orginal:B_WK_OIDN":1587233,"orginal:E_WK_OIDN":1587234,"orginal:STATUS":4,"orginal:LBLSTATUS":"in gebruik","orginal:MORF":103,"orginal:LBLMORF":"weg bestaande uit één rijbaan","orginal:WEGCAT":"S1","orginal:LBLWEGCAT":"secundaire weg type 1","orginal:LSTRNMID":61282,"orginal:LSTRNM":"Ieperse Steenweg","orginal:RSTRNMID":61282,"orginal:RSTRNM":"Ieperse Steenweg","orginal:BEHEER":"AWV315","orginal:LBLBEHEER":"Agentschap Wegen en Verkeer - District Oostende","orginal:METHODE":2,"orginal:LBLMETHOD":"ingemeten","orginal:OPNDATUM":"20161012T132044","orginal:BEGINTIJD":"20161012T134046","orginal:BEGINORG":"AWV","orginal:LBLBGNORG":"Agentschap Wegen en Verkeer","orginal:TGBEP":1,"orginal:LBLTGBEP":"openbare weg","highway":"unclassified"},"geometry":{"type":"LineString","coordinates":[[2.680036425590515,51.01971441247798],[2.680014967918396,51.019792025982014]]}},{"type":"Feature","properties":{"orginal:WS_OIDN":793620,"orginal:WS_UIDN":"793620_2","orginal:WS_GIDN":"793620_2","orginal:B_WK_OIDN":1587239,"orginal:E_WK_OIDN":1587233,"orginal:STATUS":4,"orginal:LBLSTATUS":"in gebruik","orginal:MORF":103,"orginal:LBLMORF":"weg bestaande uit één rijbaan","orginal:WEGCAT":"S1","orginal:LBLWEGCAT":"secundaire weg type 1","orginal:LSTRNMID":61282,"orginal:LSTRNM":"Ieperse Steenweg","orginal:RSTRNMID":61282,"orginal:RSTRNM":"Ieperse Steenweg","orginal:BEHEER":"AWV315","orginal:LBLBEHEER":"Agentschap Wegen en Verkeer - District Oostende","orginal:METHODE":2,"orginal:LBLMETHOD":"ingemeten","orginal:OPNDATUM":"20161012T132044","orginal:BEGINTIJD":"20161012T134046","orginal:BEGINORG":"AWV","orginal:LBLBGNORG":"Agentschap Wegen en Verkeer","orginal:TGBEP":1,"orginal:LBLTGBEP":"openbare weg","highway":"unclassified"},"geometry":{"type":"LineString","coordinates":[[2.6804119348526,51.018442207393605],[2.680036425590515,51.01971441247798]]}},{"type":"Feature","properties":{"orginal:WS_OIDN":840193,"orginal:WS_UIDN":"840193_1","orginal:WS_GIDN":"840193_1","orginal:B_WK_OIDN":1680385,"orginal:E_WK_OIDN":1907840,"orginal:STATUS":4,"orginal:LBLSTATUS":"in gebruik","orginal:MORF":103,"orginal:LBLMORF":"weg bestaande uit één rijbaan","orginal:WEGCAT":"-8","orginal:LBLWEGCAT":"niet gekend","orginal:LSTRNMID":61447,"orginal:LSTRNM":"Zwart-Paardstraat","orginal:RSTRNMID":61447,"orginal:RSTRNM":"Zwart-Paardstraat","orginal:BEHEER":"38025","orginal:LBLBEHEER":"Stad Veurne","orginal:METHODE":2,"orginal:LBLMETHOD":"ingemeten","orginal:OPNDATUM":"20140220T143532","orginal:BEGINTIJD":"20140220T143532","orginal:BEGINORG":"AGIV","orginal:LBLBGNORG":"Agentschap voor Geografische Informatie Vlaanderen","orginal:TGBEP":1,"orginal:LBLTGBEP":"openbare weg","highway":"unclassified"},"geometry":{"type":"LineString","coordinates":[[2.6782983541488647,51.019268975942396],[2.678314447402954,51.019225106961215],[2.678437829017639,51.019029383308634],[2.6785022020339966,51.01894164485134],[2.6787060499191284,51.01874929457554],[2.6789742708206177,51.01854344515087],[2.6790761947631836,51.018482702523045],[2.6794570684432983,51.01831059797874],[2.680535316467285,51.01744669100708],[2.6805567741394043,51.01743319233296],[2.6806640625,51.01741969365489],[2.680717706680298,51.01741294431437]]}},{"type":"Feature","properties":{"orginal:WS_OIDN":793619,"orginal:WS_UIDN":"793619_2","orginal:WS_GIDN":"793619_2","orginal:B_WK_OIDN":1587237,"orginal:E_WK_OIDN":1587239,"orginal:STATUS":4,"orginal:LBLSTATUS":"in gebruik","orginal:MORF":103,"orginal:LBLMORF":"weg bestaande uit één rijbaan","orginal:WEGCAT":"S1","orginal:LBLWEGCAT":"secundaire weg type 1","orginal:LSTRNMID":61282,"orginal:LSTRNM":"Ieperse Steenweg","orginal:RSTRNMID":61282,"orginal:RSTRNM":"Ieperse Steenweg","orginal:BEHEER":"AWV315","orginal:LBLBEHEER":"Agentschap Wegen en Verkeer - District Oostende","orginal:METHODE":2,"orginal:LBLMETHOD":"ingemeten","orginal:OPNDATUM":"20161012T132044","orginal:BEGINTIJD":"20161012T134046","orginal:BEGINORG":"AWV","orginal:LBLBGNORG":"Agentschap Wegen en Verkeer","orginal:TGBEP":1,"orginal:LBLTGBEP":"openbare weg","highway":"unclassified"},"geometry":{"type":"LineString","coordinates":[[2.6805245876312256,51.01807100039261],[2.6804119348526,51.018442207393605]]}},{"type":"Feature","properties":{"orginal:WS_OIDN":874175,"orginal:WS_UIDN":"874175_1","orginal:WS_GIDN":"874175_1","orginal:B_WK_OIDN":1748349,"orginal:E_WK_OIDN":1622313,"orginal:STATUS":4,"orginal:LBLSTATUS":"in gebruik","orginal:MORF":103,"orginal:LBLMORF":"weg bestaande uit één rijbaan","orginal:WEGCAT":"-8","orginal:LBLWEGCAT":"niet gekend","orginal:LSTRNMID":61384,"orginal:LSTRNM":"Schaapstraat","orginal:RSTRNMID":61384,"orginal:RSTRNM":"Schaapstraat","orginal:BEHEER":"38025","orginal:LBLBEHEER":"Stad Veurne","orginal:METHODE":2,"orginal:LBLMETHOD":"ingemeten","orginal:OPNDATUM":"20140220T143532","orginal:BEGINTIJD":"20140220T143532","orginal:BEGINORG":"AGIV","orginal:LBLBGNORG":"Agentschap voor Geografische Informatie Vlaanderen","orginal:TGBEP":1,"orginal:LBLTGBEP":"openbare weg","highway":"unclassified"},"geometry":{"type":"LineString","coordinates":[[2.675117254257202,51.01596856284394],[2.6751869916915894,51.015917941181954],[2.675444483757019,51.01561758485096],[2.6755142211914062,51.015550088778525],[2.6755625009536743,51.015519715513875],[2.675616145133972,51.01549946665972],[2.6756536960601807,51.015492717039706],[2.6757287979125977,51.015496091849855],[2.6758307218551636,51.01551296589682],[2.676098942756653,51.015583836827005],[2.6768070459365845,51.01583357162255],[2.6768821477890015,51.015867319464746],[2.676967978477478,51.01592131596115],[2.6771557331085205,51.01605968169619],[2.677472233772278,51.01617442369991],[2.678142786026001,51.01639040787785],[2.678266167640686,51.01642078057219],[2.6783573627471924,51.01642078057219],[2.678443193435669,51.01640390685557],[2.6784807443618774,51.01639040787785],[2.678545117378235,51.016353285668856]]}},{"type":"Feature","properties":{"orginal:WS_OIDN":863678,"orginal:WS_UIDN":"863678_1","orginal:WS_GIDN":"863678_1","orginal:B_WK_OIDN":1769537,"orginal:E_WK_OIDN":1727357,"orginal:STATUS":4,"orginal:LBLSTATUS":"in gebruik","orginal:MORF":103,"orginal:LBLMORF":"weg bestaande uit één rijbaan","orginal:WEGCAT":"-8","orginal:LBLWEGCAT":"niet gekend","orginal:LSTRNMID":61430,"orginal:LSTRNM":"Wijdouwbeekstraat","orginal:RSTRNMID":61430,"orginal:RSTRNM":"Wijdouwbeekstraat","orginal:BEHEER":"38025","orginal:LBLBEHEER":"Stad Veurne","orginal:METHODE":2,"orginal:LBLMETHOD":"ingemeten","orginal:OPNDATUM":"20140220T143532","orginal:BEGINTIJD":"20140220T143532","orginal:BEGINORG":"AGIV","orginal:LBLBGNORG":"Agentschap voor Geografische Informatie Vlaanderen","orginal:TGBEP":1,"orginal:LBLTGBEP":"openbare weg","highway":"unclassified"},"geometry":{"type":"LineString","coordinates":[[2.6808571815490723,51.016943862741954],[2.681018114089966,51.0168831180186],[2.681093215942383,51.01683924678005]]}}]}